{
  "multipart": [
    {
      "apply": {
        "model": "minecraft:block/lightning_rod",
        "x": 180
      },
      "when": {
        "AND": [
          {
            "facing": "down"
          },
          {
            "powered": "false"
          }
        ]
      }
    },
    {
      "apply": {
        "model": "minecraft:block/lightning_rod_on",
        "x": 180
      },
      "when": {
        "AND": [
          {
            "facing": "down"
          },
          {
            "powered": "true"
          }
        ]
      }
    },
    {
      "apply": {
        "model": "minecraft:block/lightning_rod",
        "x": 90,
        "y": 90
      },
      "when": {
        "AND": [
          {
            "facing": "east"
          },
          {
            "powered": "false"
          }
        ]
      }
    },
    {
      "apply": {
        "model": "minecraft:block/lightning_rod_on",
        "x": 90,
        "y": 90
      },
      "when": {
        "AND": [
          {
            "facing": "east"
          },
          {
            "powered": "true"
          }
        ]
      }
    },
    {
      "apply": {
        "model": "minecraft:block/lightning_rod",
        "x": 90
      },
      "when": {
        "AND": [
          {
            "facing": "north"
          },
          {
            "powered": "false"
          }
        ]
      }
    },
    {
      "apply": {
        "model": "minecraft:block/lightning_rod_on",
        "x": 90
      },
      "when": {
        "AND": [
          {
            "facing": "north"
          },
          {
            "powered": "true"
          }
        ]
      }
    },
    {
      "apply": {
        "model": "minecraft:block/lightning_rod",
        "x": 90,
        "y": 180
      },
      "when": {
        "AND": [
          {
            "facing": "south"
          },
          {
            "powered": "false"
          }
        ]
      }
    },
    {
      "apply": {
        "model": "minecraft:block/lightning_rod_on",
        "x": 90,
        "y": 180
      },
      "when": {
        "AND": [
          {
            "facing": "south"
          },
          {
            "powered": "true"
          }
        ]
      }
    },
    {
      "apply": {
        "model": "minecraft:block/lightning_rod"
      },
      "when": {
        "AND": [
          {
            "facing": "up"
          },
          {
            "powered": "false"
          }
        ]
      }
    },
    {
      "apply": {
        "model": "minecraft:block/lightning_rod_on"
      },
      "when": {
        "AND": [
          {
            "facing": "up"
          },
          {
            "powered": "true"
          }
        ]
      }
    },
    {
      "apply": {
        "model": "minecraft:block/lightning_rod",
        "x": 90,
        "y": 270
      },
      "when": {
        "AND": [
          {
            "facing": "west"
          },
          {
            "powered": "false"
          }
        ]
      }
    },
    {
      "apply": {
        "model": "minecraft:block/lightning_rod_on",
        "x": 90,
        "y": 270
      },
      "when": {
        "AND": [
          {
            "facing": "west"
          },
          {
            "powered": "true"
          }
        ]
      }
    },
    {
      "apply": [
        {
          "model": "grid_visible_block_edges:block/main",
          "uvlock": false,
          "x": 0
        },
        {
          "model": "grid_visible_block_edges:block/main",
          "uvlock": false,
          "x": 90
        },
        {
          "model": "grid_visible_block_edges:block/main",
          "uvlock": false,
          "x": 180
        },
        {
          "model": "grid_visible_block_edges:block/main",
          "uvlock": false,
          "x": 270
        }
      ],
      "when": {
        "AND": []
      }
    }
  ]
}